pytgcalls_hikka/__init__.py
pytgcalls_hikka/__version__.py
pytgcalls_hikka/binding.py
pytgcalls_hikka/environment.py
pytgcalls_hikka/exceptions.py
pytgcalls_hikka/ffprobe.py
pytgcalls_hikka/file_manager.py
pytgcalls_hikka/pytgcalls_hikka.py
pytgcalls_hikka/pytgcalls_session.py
pytgcalls_hikka/scaffold.py
pytgcalls_hikka/stream_type.py
pytgcalls_hikka/sync.py
pytgcalls_hikka/version_manager.py
pytgcalls_hikka/custom_api/__init__.py
pytgcalls_hikka/custom_api/custom_api.py
pytgcalls_hikka/handlers/__init__.py
pytgcalls_hikka/handlers/handlers_holder.py
pytgcalls_hikka/media_devices/__init__.py
pytgcalls_hikka/media_devices/device_info.py
pytgcalls_hikka/media_devices/media_devices.py
pytgcalls_hikka/media_devices/screen_info.py
pytgcalls_hikka/methods/__init__.py
pytgcalls_hikka/methods/core/__init__.py
pytgcalls_hikka/methods/core/binding_runner.py
pytgcalls_hikka/methods/core/join_voice_call.py
pytgcalls_hikka/methods/core/leave_voice_call.py
pytgcalls_hikka/methods/core/set_video_call_status.py
pytgcalls_hikka/methods/decorators/__init__.py
pytgcalls_hikka/methods/decorators/on_closed_voice_chat.py
pytgcalls_hikka/methods/decorators/on_group_call_invite.py
pytgcalls_hikka/methods/decorators/on_kicked.py
pytgcalls_hikka/methods/decorators/on_left.py
pytgcalls_hikka/methods/decorators/on_participants_change.py
pytgcalls_hikka/methods/decorators/on_raw_update.py
pytgcalls_hikka/methods/decorators/on_stream_end.py
pytgcalls_hikka/methods/groups/__init__.py
pytgcalls_hikka/methods/groups/active_calls.py
pytgcalls_hikka/methods/groups/calls.py
pytgcalls_hikka/methods/groups/change_volume_call.py
pytgcalls_hikka/methods/groups/get_active_call.py
pytgcalls_hikka/methods/groups/get_call.py
pytgcalls_hikka/methods/groups/get_participants.py
pytgcalls_hikka/methods/groups/join_group_call.py
pytgcalls_hikka/methods/groups/leave_group_call.py
pytgcalls_hikka/methods/handlers/__init__.py
pytgcalls_hikka/methods/handlers/raw_update_handler.py
pytgcalls_hikka-0.9.8.dist-info/LICENSE
pytgcalls_hikka-0.9.8.dist-info/METADATA
pytgcalls_hikka-0.9.8.dist-info/WHEEL
pytgcalls_hikka-0.9.8.dist-info/top_level.txt
pytgcalls_hikka-0.9.8.dist-info/RECORD
