Metadata-Version: 2.1
Name: pytgcalls_hikka
Version: 0.9.8
Summary: Async client API for the Telegram Calls.
Author-email: Laky-64 <iraci.matteo@gmail.com>
License: GNU LESSER GENERAL PUBLIC LICENSE
Project-URL: Homepage, https://pytgcalls.github.io/
Project-URL: Repository, https://github.com/pussyklller/pytgcalls_hikka.git
Project-URL: Documentation, https://pytgcalls.github.io/PyTgCalls
Project-URL: Changelog, https://pytgcalls.github.io/PyTgCalls/Changelogs
Keywords: audio,python,library,video,telegram,stream,ffmpeg,cpp,webrtc,voice-chat,voip,group-chat,video-calls,calls,video-chat,pytgcalls,ntgcalls,tgcalls,py-tgcalls,pyrogram,telethon
Classifier: License :: OSI Approved :: GNU Lesser General Public License v3 (LGPLv3)
Classifier: Operating System :: OS Independent
Classifier: Programming Language :: Python :: 3
Classifier: Programming Language :: Python :: 3 :: Only
Classifier: Programming Language :: Python :: 3.8
Classifier: Programming Language :: Python :: 3.9
Classifier: Programming Language :: Python :: 3.10
Classifier: Programming Language :: Python :: 3.11
Requires-Python: >=3.8
License-File: LICENSE
Requires-Dist: aiohttp >=3.9.3
Requires-Dist: ntgcalls <1.3.0,>=1.2.0
Requires-Dist: psutil
Requires-Dist: screeninfo
Requires-Dist: deprecation
Provides-Extra: nodejs
Requires-Dist: nodejs >=18.0.0 ; extra == 'nodejs'
Provides-Extra: pyrogram
Requires-Dist: pyrogram >=1.2.20 ; extra == 'pyrogram'
Provides-Extra: telethon
Requires-Dist: telethon >=1.24.0 ; extra == 'telethon'
